Metadata-Version: 1.0
Name: test-zws
Version: 0.1
Summary: Gaussian and Binormial distributions
Home-page: UNKNOWN
Author: UNKNOWN
Author-email: UNKNOWN
License: UNKNOWN
Platform: UNKNOWN
